{
  "id": "aramex",
  "exported_at": "2025-09-11T04:41:42.486Z",
  "exported_from": "firebase_settings",
  "data": {
    "shipperInfo": {
      "stateProvince": "Muscat",
      "addressLine2": "",
      "postalCode": "111",
      "countryCode": "OM",
      "addressLine1": "Al Hail",
      "city": "Muscat",
      "companyName": "Spirit Hub",
      "contactName": "Said",
      "phoneNumber": "92506030"
    },
    "enableLogging": true,
    "services": [
      {
        "customLabel": "Aramex Domestic (OND)",
        "enabled": true,
        "id": "OND",
        "type": "domestic",
        "name": "Aramex Domestic"
      },
      {
        "id": "CDS",
        "customLabel": "Cash on Delivery (CDS)",
        "name": "Cash on Delivery",
        "enabled": true,
        "type": "domestic"
      },
      {
        "enabled": true,
        "name": "Aramex Express",
        "customLabel": "Aramex Express (EPX)",
        "type": "international",
        "id": "EPX"
      },
      {
        "id": "PPX",
        "name": "Aramex Priority",
        "customLabel": "Aramex Priority (PPX)",
        "type": "international",
        "enabled": true
      },
      {
        "customLabel": "Aramex Ground (GRD)",
        "enabled": true,
        "id": "GRD",
        "type": "international",
        "name": "Aramex Ground"
      }
    ],
    "enabled": true,
    "autoCreateShipment": true,
    "testMode": false,
    "credentials": {
      "accountPin": "617333",
      "username": "info@spirithubcafe.com",
      "source": "24",
      "accountNumber": "71925275",
      "accountCountryCode": "OM",
      "password": "ChemicalShared@33",
      "accountEntity": "MCT",
      "apiVersion": "v1.0"
    }
  }
}